opale/__init__.py
opale/support.py
opale/version.py
opale-0.1.0.dist-info/LICENSE
opale-0.1.0.dist-info/METADATA
opale-0.1.0.dist-info/WHEEL
opale-0.1.0.dist-info/entry_points.txt
opale-0.1.0.dist-info/top_level.txt
opale-0.1.0.dist-info/RECORD
